<?xml version="1.0" standalone="yes"?>
<pysystest type="auto" state="runnable">
    
  <description> 
    <title>Assertions - check assertLastGrep</title>    
    <purpose><![CDATA[
Checks a variety of input into the assertLastGrep method of the BaseTest
]]>
    </purpose>
  </description>

  <classification>
    <groups>
      <group>asserts</group>
    </groups>
  </classification>

  <data>
    <class name="PySysTest" module="run"/>
  </data>
  
  <traceability>
    <requirements>
      <requirement id=""/>     
    </requirements>
  </traceability>
</pysystest>
